[
  {
    "identifier": "arbitrum",
    "name": "Arbitrum",
    "description": "The ultimate Layer 2 scaling solution designed to enhance your Ethereum experience.",
    "icon": "../public/protocol/arbitrum.png",
    "chains": ["arbitrum"],
    "category": [
      "aave_v3",
      "aura_bal_vault",
      "balancer_v2_composable_stable_v1",
      "balancer_v2_composable_stable_v3",
      "balancer_v2_composable_stable_v4",
      "balancer_v2_composable_stable_v5",
      "balancer_v2_composable_stable_v6",
      "balancer_v2_weighted_2",
      "balancer_v2_weighted_v1",
      "balancer_v2_weighted_v2",
      "balancer_v2_weighted_v3",
      "balancer_v2_weighted_v4",
      "bebop_v3_fok",
      "beefy_vault_v7",
      "camelot_v3",
      "compound_v3",
      "curve_main_stable_swap_plain",
      "curve_main_stable_swap_plain_1",
      "curve_stable_ng_meta",
      "curve_stable_ng_plain",
      "curve_stable_plain",
      "curve_tri_crypto_ng",
      "curve_two_crypto_ng",
      "dodo_v1",
      "dodo_v2_dpp",
      "dodo_v2_dsp",
      "dodo_v2_dvm",
      "fluid_dex",
      "hashflow_v3_fok",
      "integral",
      "kelp_wrseth_eth",
      "maverick_v2",
      "pancakeswap_v3",
      "peapods",
      "pendle",
      "pendle_v3",
      "pendle_v4",
      "pendle_v5",
      "sushiswap_v3",
      "uniswap_v2",
      "uniswap_v3",
      "usdx_susdx",
      "zerox_v2_fok"
    ],
    "website": "https://arbitrum.io/",
    "docs": "https://docs.arbitrum.io/welcome/get-started",
    "socials": {
      "twitter": "https://x.com/arbitrum",
      "discord": "http://discord.com/invite/arbitrum",
      "telegram": "https://t.me/arbitrum",
      "github": "https://github.com/OffchainLabs/arbitrum-docs"
    },
    "reference": []
  },
  {
    "identifier": "avalanche",
    "name": "Avalanche",
    "description": "Avalanche is a Layer 1 blockchain platform designed for building decentralized applications (dApps) and custom blockchain networks",
    "icon": "../public/protocol/avalanche.png",
    "chains": ["avalanche"],
    "category": [
      "aave_v2",
      "aave_v3",
      "beefy_vault_v7",
      "benqi_avax_savax",
      "benqi_core_markets",
      "curve_stable_ng_plain",
      "curve_stable_plain",
      "fraxswap",
      "hashflow_v3_fok",
      "pangolin",
      "uniswap_v3"
    ],
    "website": "https://www.avax.network/",
    "docs": "https://build.avax.network/docs",
    "socials": {
      "twitter": "https://x.com/avax",
      "discord": "https://discord.com/invite/RwXY7P6",
      "telegram": "https://t.me/avalancheavax",
      "github": "https://github.com/ava-labs"
    },
    "reference": []
  },
  {
    "identifier": "base",
    "name": "Base",
    "description": "Base is a secure, low-cost, builder-friendly Ethereum L2 built to bring the next billion users onchain.",
    "icon": "../public/protocol/base.png",
    "chains": ["base"],
    "category": [
      "aerodrome",
      "aerodrome_basic_volatile",
      "alienbase_v2",
      "aura_bal_vault",
      "bebop_v3_fok",
      "beefy_protocol",
      "beefy_vault_v7",
      "compound_v3",
      "curve_crypto_plain",
      "curve_stable_ng_plain",
      "curve_stable_plain",
      "curve_tri_crypto_ng",
      "curve_two_crypto_ng",
      "fluid_dex",
      "hashflow_v3_fok",
      "kelp_wrseth_eth",
      "maverick_v2",
      "moonwell_lend",
      "morpho",
      "morpho_v1_1",
      "pancakeswap_v2",
      "pancakeswap_v3",
      "peapods",
      "pendle_v5",
      "seamless_aave",
      "seamless_wsusdbc",
      "seamless_wsweth",
      "stkwell_well",
      "sushiswap_v3",
      "uniswap_v2",
      "uniswap_v3",
      "wagmi",
      "zerolend",
      "zerox_v2_fok"
    ],
    "website": "https://www.base.org/",
    "docs": "https://docs.base.org/",
    "socials": {
      "twitter": "https://x.com/buildonbase",
      "discord": "https://discord.com/invite/buildonbase",
      "telegram": "",
      "github": "https://github.com/base"
    },
    "reference": []
  },
  {
    "identifier": "berachain",
    "name": "Berachain",
    "description": "Berachain is a Layer-1 blockchain designed to be a liquidity-focused, EVM-identical platform that reimagines blockchain consensus and token utility.",
    "icon": "../public/protocol/berachain.png",
    "chains": ["berachain"],
    "category": [
      "bex_composable_stable_v6",
      "bex_weighted_v5",
      "burrbear_composable_stable_v6",
      "burrbear_weighted_v4",
      "kodiak_uniswap_v2",
      "kodiak_v3"
    ],
    "website": "https://www.berachain.com/",
    "docs": "https://docs.berachain.com/",
    "socials": {
      "twitter": "https://x.com/berachain",
      "discord": "https://discord.com/invite/berachain",
      "telegram": "https://t.me/BerachainPortal",
      "github": "https://github.com/berachain"
    },
    "reference": []
  },
  {
    "identifier": "blast",
    "name": "Blast",
    "description": "An Ethereum Layer 2 (L2) solution that uniquely offers native yield for both ETH and stablecoins.",
    "icon": "../public/protocol/blast.webp",
    "chains": ["blast"],
    "category": [
      "kelp_wrseth_eth",
      "ring_v2",
      "thruster_v2_1",
      "thruster_v2_2",
      "thruster_v3",
      "zerolend"
    ],
    "website": "https://blast.io",
    "docs": "https://docs.blast.io/building/network-information",
    "socials": {
      "twitter": "https://x.com/Blast",
      "discord": "https://discord.com/invite/blast-l2",
      "telegram": "",
      "github": "https://github.com/blast-io"
    },
    "reference": []
  },
  {
    "identifier": "bnb",
    "name": "BNB",
    "description": "The BNB Chain is a blockchain ecosystem developed by Binance capable of supporting many different types of activity.",
    "icon": "../public/protocol/bnb.png",
    "chains": ["bnb"],
    "category": [
      "bebop_v3_fok",
      "beefy_vault_v7",
      "curve_stable_ng_plain",
      "curve_two_crypto_ng",
      "hashflow_v3_fok",
      "pancakeswap_v2",
      "pancakeswap_v3",
      "pendle",
      "pendle_v3",
      "pendle_v4",
      "pendle_v5",
      "uniswap_v2",
      "uniswap_v3",
      "usdx_susdx"
    ],
    "website": "https://www.bnbchain.org/",
    "docs": "https://docs.bnbchain.org/",
    "socials": {
      "twitter": "https://docs.bnbchain.org/",
      "discord": "https://discord.com/invite/bnbchain",
      "telegram": "https://t.me/bnbchain",
      "github": "https://github.com/bnb-chain"
    },
    "reference": []
  },
  {
    "identifier": "ethereum",
    "name": "Ethereum",
    "description": "Ethereum is a decentralized blockchain and development platform with smart contract functionality.",
    "icon": "../public/protocol/ethereum.png",
    "chains": ["ethereum"],
    "category": [
      "aave_v2",
      "aave_v3",
      "affine_ultreths_eth",
      "apeswap",
      "aura_bal_vault",
      "balancer_cowamm",
      "balancer_v2_composable_stable_v1",
      "balancer_v2_composable_stable_v3",
      "balancer_v2_composable_stable_v4",
      "balancer_v2_composable_stable_v5",
      "balancer_v2_composable_stable_v6",
      "balancer_v2_weighted_2",
      "balancer_v2_weighted_v1",
      "balancer_v2_weighted_v2",
      "balancer_v2_weighted_v3",
      "balancer_v2_weighted_v4",
      "balancer_v3_stable",
      "balancer_v3_weighted",
      "bebop_v3_fok",
      "bebop_v3_pf_lob",
      "beefy_protocol",
      "beefy_vault_v7",
      "binance_wbeth_eth",
      "compound_v3",
      "compv2_cbat_bat",
      "compv2_ccomp_comp",
      "compv2_cdai_dai",
      "compv2_ceth_eth",
      "compv2_clink_link",
      "compv2_cmkr_mkr",
      "compv2_csushi_sushi",
      "compv2_ctusd_tusd",
      "compv2_cuni_uni",
      "compv2_cusdc_usdc",
      "compv2_cusdp_usdp",
      "compv2_cwbtc_wbtc",
      "compv2_cyfi_yfi",
      "compv2_czrx_zrx",
      "convex_finance",
      "convex_finance_frax_fpis",
      "convex_finance_fx_protocol",
      "convex_finance_prisma",
      "curve_crvusd",
      "curve_crypto_plain",
      "curve_main_stable_swap_plain",
      "curve_main_stable_swap_plain_1",
      "curve_stable_ng_meta",
      "curve_stable_ng_plain",
      "curve_stable_plain",
      "curve_tri_crypto_ng",
      "curve_two_crypto_ng",
      "defiswap",
      "dodo_v1",
      "dodo_v2_dpp",
      "dodo_v2_dsp",
      "dodo_v2_dvm",
      "dooar",
      "etherfi_eeth_eth",
      "etherfi_weeth_eeth",
      "euler_v2",
      "fluid_dex",
      "fluid_fusdc_usdc",
      "flux_finance",
      "fraxswap",
      "frxeth_eth",
      "gho_stkgho",
      "gho_usdc",
      "gho_usdt",
      "hashflow_v3_fok",
      "integral",
      "kelp_rseth_eth",
      "kyberswap_classic",
      "lido_steth_weth",
      "lido_steth_wsteth",
      "maker_dai_sdai",
      "maker_dai_usds",
      "maker_lite_psm",
      "maker_mkr_sky",
      "maker_psm",
      "maker_usds_susds",
      "mantle_meth_eth",
      "maverick_v1",
      "maverick_v2",
      "morpho",
      "morpho_v1_1",
      "mountain_wusdm_usdm",
      "native_pmm_fok",
      "origin_swap",
      "pancakeswap_v2",
      "pancakeswap_v3",
      "peapods",
      "pendle",
      "pendle_v3",
      "pendle_v4",
      "pendle_v5",
      "pirex_apxeth_pxeth",
      "puffer_finance",
      "resolv_wstusr",
      "reth_eth",
      "sakeswap",
      "sdola_dola",
      "sfrax_frax",
      "sfrxeth_frxeth",
      "shibaswap",
      "solidly_v3",
      "sparklend",
      "stader_ethx_eth",
      "stakestone_stone_eth",
      "stusd_usda",
      "susde_usde",
      "sushiswap",
      "swapr",
      "swell_rsweth_eth",
      "sweth_eth",
      "symbiotic",
      "tenderswap_lpeth_eeth",
      "tenderswap_lpeth_eth",
      "tenderswap_lpeth_ethx",
      "tenderswap_lpeth_meth",
      "tenderswap_lpeth_steth",
      "tenderswap_lpeth_sweth",
      "treehouse",
      "uniswap_v2",
      "uniswap_v3",
      "usd0pp_usd0",
      "usdl_wusdl",
      "usdx_susdx",
      "usualsp_usuals",
      "usualx_usual",
      "uwu_lend",
      "valantis_hot_amm",
      "valantis_hot_fok_usdc_weth",
      "wagmi",
      "yearn_v2_balancer",
      "yearn_v2_curve",
      "yearn_v3_0_1",
      "yearn_v3_0_2",
      "yearn_v3_0_3",
      "yearn_v3_0_4",
      "yearn_yeth_styeth",
      "yusd_usdt",
      "zeroex_pf_lob",
      "zerolend",
      "zerox_v2_fok"
    ],
    "website": "https://ethereum.org/",
    "docs": "https://ethereum.org/en/developers/docs/",
    "socials": {
      "twitter": "https://x.com/ethereum",
      "discord": "https://discord.com/invite/ethereum-org",
      "telegram": "",
      "github": "https://github.com/ethereum"
    },
    "reference": []
  },
  {
    "identifier": "gnosis",
    "name": "Gnosis",
    "description": "Full stack decentralization—infrastructure and applications for an open internet.",
    "icon": "../public/protocol/gnosis.png",
    "chains": ["gnosis"],
    "category": [
      "aave_v3",
      "balancer_v2_composable_stable_v3",
      "balancer_v2_composable_stable_v4",
      "balancer_v2_composable_stable_v5",
      "balancer_v2_composable_stable_v6",
      "balancer_v2_lbp",
      "balancer_v2_weighted_v2",
      "balancer_v2_weighted_v3",
      "balancer_v2_weighted_v4",
      "balancer_v3_stable",
      "balancer_v3_weighted",
      "beefy_vault_v7",
      "curve_main_stable_swap_plain",
      "curve_stable_ng_meta",
      "curve_stable_ng_plain",
      "curve_stable_plain",
      "curve_two_crypto_ng",
      "sdai_wxdai",
      "sparklend",
      "uniswap_v3"
    ],
    "website": "https://www.gnosis.io/",
    "docs": "https://docs.gnosis.example.com",
    "socials": {
      "twitter": "http://x.com/gnosisdao",
      "discord": "https://discord.com/invite/gnosis",
      "telegram": "",
      "github": "https://github.com/gnosis"
    },
    "reference": []
  },
  {
    "identifier": "linea",
    "name": "Linea",
    "description": "Linea is a fully EVM equivalent zero-knowledge rollup (zk-rollup), designed to scale Ethereum with higher throughput and lowered transaction fees.",
    "icon": "../public/protocol/linea.png",
    "chains": ["linea"],
    "category": [
      "beefy_vault_v7",
      "kelp_wrseth_eth",
      "mendi_adjusted",
      "mendi_medai_dai",
      "mendi_mewbtc_wbtc",
      "mendi_pools",
      "pancakeswap_v2",
      "pancakeswap_v3",
      "zerolend"
    ],
    "website": "https://linea.build/",
    "docs": "https://docs.linea.build/",
    "socials": {
      "twitter": "https://x.com/LineaBuild",
      "discord": "https://discord.com/invite/linea",
      "telegram": "",
      "github": ""
    },
    "reference": []
  },
  {
    "identifier": "mantle",
    "name": "Mantle",
    "description": "A Layer 2 scaling solution for Ethereum, built on top of the Ethereum blockchain.",
    "icon": "../public/protocol/mantle.png",
    "chains": ["mantle"],
    "category": ["compound_v3", "pendle_v3", "pendle_v4", "pendle_v5"],
    "website": "https://www.mantle.xyz/",
    "docs": "https://docs.mantle.xyz/network",
    "socials": {
      "twitter": "https://x.com/Mantle_Official",
      "discord": "https://discord.com/invite/0xMantle",
      "telegram": "https://t.me/mantlenetwork",
      "github": "https://github.com/mantlenetworkio"
    },
    "reference": []
  },
  {
    "identifier": "optimism",
    "name": "Optimism",
    "description": "An extension to Ethereum which enables users and developers to benefit from the latter's strong security guarantees while being cheaper and faster.",
    "icon": "../public/protocol/optimism.png",
    "chains": ["optimism"],
    "category": [
      "aave_v3",
      "bebop_v3_fok",
      "beets_v2_composable_stable_v4",
      "beets_v2_composable_stable_v5",
      "beets_v2_composable_stable_v6",
      "beets_v2_weighted_2",
      "beets_v2_weighted_v1",
      "beets_v2_weighted_v2",
      "beets_v2_weighted_v3",
      "beets_v2_weighted_v4",
      "compound_v3",
      "curve_stable_ng_plain",
      "curve_stable_plain",
      "curve_tri_crypto_ng",
      "hashflow_v3_fok",
      "kelp_wrseth_eth",
      "moonwell_lend",
      "pendle",
      "solidly_v3",
      "stkwell_well",
      "uniswap_v2",
      "uniswap_v3",
      "velodrome_v3",
      "wagmi"
    ],
    "website": "https://www.optimism.io/",
    "docs": "https://docs.optimism.io/",
    "socials": {
      "twitter": "https://x.com/optimism",
      "discord": "https://discord.com/invite/optimism",
      "telegram": "",
      "github": "https://github.com/ethereum-optimism"
    },
    "reference": []
  },
  {
    "identifier": "polygon",
    "name": "Polygon",
    "description": "A blockchain framework aimed at enhancing the Ethereum network by reducing transaction fees and increasing transaction speed.",
    "icon": "../public/protocol/polygon.png",
    "chains": ["polygon"],
    "category": [
      "aave_v2",
      "aave_v3",
      "balancer_v2_composable_stable_v1",
      "balancer_v2_composable_stable_v3",
      "balancer_v2_composable_stable_v4",
      "balancer_v2_composable_stable_v5",
      "balancer_v2_composable_stable_v6",
      "balancer_v2_weighted_2",
      "balancer_v2_weighted_v1",
      "balancer_v2_weighted_v2",
      "balancer_v2_weighted_v3",
      "balancer_v2_weighted_v4",
      "compound_v3",
      "curve_crypto_plain",
      "curve_main_stable_swap_plain",
      "curve_stable_ng_plain",
      "curve_stable_plain",
      "hashflow_v3_fok",
      "quickswap",
      "quickswap_v3",
      "sushiswap",
      "uniswap_v2",
      "uniswap_v3"
    ],
    "website": "https://polygon.technology/",
    "docs": "https://docs.polygon.technology/",
    "socials": {
      "twitter": "https://x.com/0xPolygon",
      "discord": "https://discord.com/invite/0xPolygonCommunity",
      "telegram": "",
      "github": "https://github.com/maticnetwork"
    },
    "reference": []
  },
  {
    "identifier": "scroll",
    "name": "Scroll",
    "description": "An EVM-equivalent Layer 2 scaling solution for Ethereum that utilizes ZK technology.",
    "icon": "../public/protocol/scroll.png",
    "chains": ["scroll"],
    "category": [
      "beefy_vault_v7",
      "compound_v3",
      "kelp_wrseth_eth",
      "maverick_v2"
    ],
    "website": "https://scroll.io/",
    "docs": "https://docs.scroll.io/en/home/",
    "socials": {
      "twitter": "https://x.com/Scroll_ZKP",
      "discord": "https://discord.com/invite/scroll",
      "telegram": "",
      "github": "https://github.com/scroll-tech"
    },
    "reference": []
  },
  {
    "identifier": "sonic",
    "name": "Sonic",
    "description": "A fast, scalable chain optimized for gaming and NFT marketplaces that allows up to 10,000 transactions per second.",
    "icon": "../public/protocol/sonic.webp",
    "chains": ["sonic"],
    "category": [
      "curve_stable_ng_plain",
      "curve_tri_crypto_ng",
      "curve_two_crypto_ng",
      "wagmi"
    ],
    "website": "https://www.soniclabs.com/",
    "docs": "https://docs.soniclabs.com/",
    "socials": {
      "twitter": "https://x.com/SonicLabs",
      "discord": "https://discord.com/invite/3Ynr2QDSnB",
      "telegram": "http://t.me/Sonic_English",
      "github": "https://github.com/0xsoniclabs"
    },
    "reference": []
  },
  {
    "identifier": "taiko",
    "name": "Taiko",
    "description": "An Ethereum-equivalent Optimistic Rollup on the Ethereum network.",
    "icon": "../public/protocol/taiko.png",
    "chains": ["taiko"],
    "category": ["bebop_v3_fok", "curve_tri_crypto_ng", "uniswap_v3"],
    "website": "https://taiko.xyz/",
    "docs": "https://docs.taiko.xyz/",
    "socials": {
      "twitter": "https://x.com/taikoxyz",
      "discord": "https://discord.com/invite/taikoxyz",
      "telegram": "",
      "github": "https://github.com/taikoxyz"
    },
    "reference": []
  },
  {
    "identifier": "unichain",
    "name": "Unichain",
    "description": "A decentralized, high-speed Layer 2 blockchain built to scale Ethereum while enhancing liquidity across different blockchains.",
    "icon": "../public/protocol/unichain.svg",
    "chains": ["unichain"],
    "category": ["uniswap_v2", "uniswap_v3"],
    "website": "https://www.unichain.org/",
    "docs": "https://docs.unichain.org/docs",
    "socials": {
      "twitter": "https://x.com/unichain",
      "discord": "https://discord.com/invite/uniswap",
      "telegram": "",
      "github": ""
    },
    "reference": []
  }
]
